neuroforge/__init__.py
neuroforge/loader.py
neuroforge/nns.py
neuroforge/preprocessing.py
neuroforge/config/__init__.py
neuroforge/config/model-config.yml
neuroforge/ml/__init__.py
neuroforge/ml/supervised.py
neuroforge/ml/unsupervised.py
neuroforge/utils/__init__.py
neuroforge/utils/config.py
neuroforge-0.4.0.dist-info/licenses/LICENSE
neuroforge-0.4.0.dist-info/METADATA
neuroforge-0.4.0.dist-info/WHEEL
neuroforge-0.4.0.dist-info/top_level.txt
neuroforge-0.4.0.dist-info/RECORD
